opia/__init__.py
opia/docs/__init__.py
opia/geography/__init__.py
opia/geography/distance.py
opia/tests/__init__.py
opia-1.0.2.dist-info/METADATA
opia-1.0.2.dist-info/WHEEL
opia-1.0.2.dist-info/top_level.txt
opia-1.0.2.dist-info/RECORD
