Metadata-Version: 2.1
Name: opia
Version: 1.0.2
Summary: Opia Package
Home-page: https://github.com/melihcolpan/opia
Author: Melih Colpan
Author-email: melihcolpan1@gmail.com
License: MIT
Platform: UNKNOWN
Classifier: License :: OSI Approved :: MIT License
Classifier: Programming Language :: Python :: 3
Classifier: Programming Language :: Python :: 3.7
Requires-Dist: pandas
Requires-Dist: scipy
